Metadata-Version: 2.0
Name: dms2dfe
Version: 1.0.6.5
Summary: Pipeline to analyse Deep Mutational Scanning (DMS) experiments in terms of Distribution of Fitness Effects (DFE)
Home-page: https://github.com/rraadd88/dms2dfe
Author: Rohan Dandage
Author-email: rraadd_8@hotmail.com,rohan@igib.in
License: General Public License v. 3
Download-URL: https://github.com/rraadd88/dms2dfe/archive/master.zip
Keywords: bioinformatics,Deep sequencing,molecular evolution
Platform: Linux 64bit-Debian (Tested on Ubuntu 12.04)
Requires-Dist: numpy (==1.13.1)
Requires-Dist: biopython (>=1.68)
Requires-Dist: pandas (>=0.18.0)
Requires-Dist: scipy (>=0.17.0)
Requires-Dist: statsmodels (==0.6.1)
Requires-Dist: scikit-learn (==0.18)
Requires-Dist: forestci (==0.1)
Requires-Dist: matplotlib (>=1.5.1)
Requires-Dist: seaborn (==0.7.0)
Requires-Dist: pysam (==0.8.4)
Requires-Dist: pychimera (==0.1.4)
Requires-Dist: scikit-bio (==0.4.1)
